emailicious/__init__.py
emailicious/config.py
emailicious/gmail.py
emailicious/main.py
emailicious/ms_graph.py
emailicious/utils.py
emailicious-0.1.2.dist-info/LICENSE
emailicious-0.1.2.dist-info/METADATA
emailicious-0.1.2.dist-info/WHEEL
emailicious-0.1.2.dist-info/entry_points.txt
emailicious-0.1.2.dist-info/RECORD
