Metadata-Version: 2.3
Name: emailicious
Version: 0.1.2
Summary: This is a Python package that automates sending of emails
Requires-Python: >=3.11
Classifier: Programming Language :: Python :: 3
Classifier: License :: OSI Approved :: MIT License
Classifier: Operating System :: OS Independent
Requires-Dist: msal (>=1.31.1)
